kaeru/__init__.py
kaeru/api.py
kaeru/cli.py
kaeru/database.py
kaeru/tables.py
kaeru-0.2.3.dist-info/entry_points.txt
kaeru-0.2.3.dist-info/WHEEL
kaeru-0.2.3.dist-info/METADATA
kaeru-0.2.3.dist-info/RECORD
